tqdm_batch/__init__.py
tqdm_batch/batch_process.py
tqdm_batch/progress_bar.py
tqdm_batch/task_wrapper.py
tqdm_batch-0.1.0.dist-info/LICENSE
tqdm_batch-0.1.0.dist-info/METADATA
tqdm_batch-0.1.0.dist-info/WHEEL
tqdm_batch-0.1.0.dist-info/top_level.txt
tqdm_batch-0.1.0.dist-info/RECORD
