Metadata-Version: 2.1
Name: tqdm-batch
Version: 0.1.0
Summary: Wrapper for tqdm and joblib to have a progressbar while batch processing
Home-page: https://github.com/dennisbakhuis/tqdm_batch
Author: Dennis Bakhuis
Author-email: pypi@bakhuis.nu
License: UNKNOWN
Platform: UNKNOWN
Classifier: Programming Language :: Python :: 3
Classifier: License :: OSI Approved :: MIT License
Classifier: Operating System :: OS Independent
Requires-Python: >=3.6
License-File: LICENSE
